Metadata-Version: 1.1
Name: ar-file
Version: 0.0.1
Summary: Unix archive file library
Home-page: https://github.com/nirenjan/ar_file
Author: Nirenjan Krishnan
Author-email: nirenjan@gmail.com
License: UNKNOWN
Platform: UNKNOWN
Classifier: Programming Language :: Python
Classifier: License :: OSI Approved :: GNU Lesser General Public License v2 (LGPLv2)
Classifier: Operating System :: OS Independent
